muxnect/__init__.py
muxnect/client.py
muxnect/server.py
muxnect-0.2.4.dist-info/DESCRIPTION.rst
muxnect-0.2.4.dist-info/METADATA
muxnect-0.2.4.dist-info/RECORD
muxnect-0.2.4.dist-info/WHEEL
muxnect-0.2.4.dist-info/entry_points.txt
muxnect-0.2.4.dist-info/metadata.json
muxnect-0.2.4.dist-info/top_level.txt
