Metadata-Version: 2.0
Name: muxnect
Version: 0.2.4
Summary: Send input to just about any interactive command-line tool through a local web server
Home-page: https://www.github.com/ritiek/muxnect
Author: Ritiek Malhotra
Author-email: ritiekmalhotra123@gmail.com
License: MIT
Download-URL: https://github.com/ritiek/muxnect/archive/v0.2.4.tar.gz
Keywords: tmux,connect,send,input,command-line,interactive,local,network
Platform: UNKNOWN
Requires-Dist: requests
Requires-Dist: Flask
Requires-Dist: libtmux
